vnet/VizOneat.py
vnet/__init__.py
vnet/_version.py
viz_oneat-1.1.0.dist-info/METADATA
viz_oneat-1.1.0.dist-info/WHEEL
viz_oneat-1.1.0.dist-info/top_level.txt
viz_oneat-1.1.0.dist-info/RECORD
