Metadata-Version: 2.1
Name: viz-oneat
Version: 1.1.0
Summary: Neural network activation visualization tool.
Home-page: https://github.com/Kapoorlabs-CAPED/VNet/
Author: Varun Kapoor
Author-email: randomaccessiblekapoor@gmail.com
Classifier: Development Status :: 3 - Alpha
Classifier: Natural Language :: English
Classifier: License :: OSI Approved :: MIT License
Classifier: Operating System :: OS Independent
Classifier: Programming Language :: Python
Classifier: Programming Language :: Python :: 3.9
Requires-Dist: oneat
